tsuite/__init__.py
tsuite/py.typed
tsuite/tsuite_test.py
tsuite/_src/__init__.py
tsuite/_src/action_space.py
tsuite/_src/action_space_test.py
tsuite/_src/agent.py
tsuite/_src/agent_test.py
tsuite/_src/bad_observation.py
tsuite/_src/bad_observation_test.py
tsuite/_src/bad_timestep.py
tsuite/_src/bad_timestep_test.py
tsuite/_src/base.py
tsuite/_src/base_test.py
tsuite/_src/causal.py
tsuite/_src/causal_test.py
tsuite/_src/crashing_env.py
tsuite/_src/crashing_env_test.py
tsuite/_src/cross_contamination.py
tsuite/_src/cross_contamination_test.py
tsuite/_src/custom.py
tsuite/_src/custom_test.py
tsuite/_src/discount.py
tsuite/_src/discount_test.py
tsuite/_src/future_leakage.py
tsuite/_src/future_leakage_test.py
tsuite/_src/knows_prerecorded_sequence.py
tsuite/_src/knows_prerecorded_sequence_test.py
tsuite/_src/language.py
tsuite/_src/language_test.py
tsuite/_src/latency.py
tsuite/_src/latency_test.py
tsuite/_src/memory.py
tsuite/_src/memory_test.py
tsuite/_src/observation_space.py
tsuite/_src/observation_space_test.py
tsuite/_src/overfit.py
tsuite/_src/overfit_test.py
tsuite/_src/reward.py
tsuite/_src/reward_test.py
tsuite/_src/sensitivity.py
tsuite/_src/sensitivity_test.py
tsuite/_src/slow_env.py
tsuite/_src/slow_env_test.py
tsuite/_src/test_utils.py
tsuite/_src/thread_safety.py
tsuite/_src/thread_safety_test.py
tsuite/_src/tsuite.py
tsuite/_src/tsuite_test.py
tsuite/_src/updater.py
tsuite/_src/updater_test.py
tsuite/_src/visual.py
tsuite/_src/visual_test.py
tsuite/_src/zero_discount.py
tsuite/_src/zero_discount_test.py
tsuite-1.0.dist-info/LICENSE
tsuite-1.0.dist-info/METADATA
tsuite-1.0.dist-info/WHEEL
tsuite-1.0.dist-info/top_level.txt
tsuite-1.0.dist-info/RECORD
