Metadata-Version: 2.1
Name: tsuite
Version: 1.0
Summary: tsuite: Get your RL agent fixed today!
Home-page: https://github.com/deepmind/tsuite
Author: DeepMind
Author-email: tsuite-devs@google.com
License: Apache 2.0
Keywords: RL testing debugging python machine learning
Classifier: Development Status :: 5 - Production/Stable
Classifier: Environment :: Console
Classifier: Intended Audience :: Science/Research
Classifier: Intended Audience :: Developers
Classifier: License :: OSI Approved :: Apache Software License
Classifier: Operating System :: OS Independent
Classifier: Programming Language :: Python
Classifier: Programming Language :: Python :: 3
Classifier: Topic :: Scientific/Engineering :: Artificial Intelligence
Classifier: Topic :: Software Development :: Testing :: Mocking
Classifier: Topic :: Software Development :: Testing :: Unit
Classifier: Topic :: Software Development :: Libraries :: Python Modules
Requires-Python: >=3.9
License-File: LICENSE
Requires-Dist: absl-py >=1.4.0
Requires-Dist: chex >=0.1.82
Requires-Dist: dm-env >=1.6
Requires-Dist: dm-haiku >=0.0.10
Requires-Dist: dm-tree >=0.1.8
Requires-Dist: jax >=0.4.14
Requires-Dist: jaxlib >=0.1.14
Requires-Dist: numpy >=1.25.0
Requires-Dist: optax >=0.1.7
